qubx/__init__.py
qubx/_nb_magic.py
qubx/backtester/__init__.py
qubx/backtester/account.py
qubx/backtester/broker.py
qubx/backtester/data.py
qubx/backtester/management.py
qubx/backtester/ome.py
qubx/backtester/optimization.py
qubx/backtester/runner.py
qubx/backtester/sentinels.py
qubx/backtester/simulated_data.py
qubx/backtester/simulated_exchange.py
qubx/backtester/simulator.py
qubx/backtester/transfers.py
qubx/backtester/utils.py
qubx/cli/__init__.py
qubx/cli/commands.py
qubx/cli/deploy.py
qubx/cli/misc.py
qubx/cli/release.py
qubx/cli/tui.py
qubx/connectors/ccxt/__init__.py
qubx/connectors/ccxt/account.py
qubx/connectors/ccxt/adapters/__init__.py
qubx/connectors/ccxt/adapters/polling_adapter.py
qubx/connectors/ccxt/broker.py
qubx/connectors/ccxt/connection_manager.py
qubx/connectors/ccxt/data.py
qubx/connectors/ccxt/exceptions.py
qubx/connectors/ccxt/exchange_manager.py
qubx/connectors/ccxt/exchanges/__init__.py
qubx/connectors/ccxt/exchanges/base.py
qubx/connectors/ccxt/exchanges/binance/broker.py
qubx/connectors/ccxt/exchanges/binance/exchange.py
qubx/connectors/ccxt/exchanges/bitfinex/bitfinex.py
qubx/connectors/ccxt/exchanges/bitfinex/bitfinex_account.py
qubx/connectors/ccxt/exchanges/hyperliquid/__init__.py
qubx/connectors/ccxt/exchanges/hyperliquid/account.py
qubx/connectors/ccxt/exchanges/hyperliquid/broker.py
qubx/connectors/ccxt/exchanges/hyperliquid/hyperliquid.py
qubx/connectors/ccxt/exchanges/kraken/kraken.py
qubx/connectors/ccxt/factory.py
qubx/connectors/ccxt/handlers/__init__.py
qubx/connectors/ccxt/handlers/base.py
qubx/connectors/ccxt/handlers/factory.py
qubx/connectors/ccxt/handlers/funding_rate.py
qubx/connectors/ccxt/handlers/liquidation.py
qubx/connectors/ccxt/handlers/ohlc.py
qubx/connectors/ccxt/handlers/open_interest.py
qubx/connectors/ccxt/handlers/orderbook.py
qubx/connectors/ccxt/handlers/quote.py
qubx/connectors/ccxt/handlers/trade.py
qubx/connectors/ccxt/reader.py
qubx/connectors/ccxt/subscription_config.py
qubx-0.7.31.dist-info/METADATA
qubx-0.7.31.dist-info/WHEEL
qubx-0.7.31.dist-info/entry_points.txt
qubx-0.7.31.dist-info/licenses/LICENSE
qubx-0.7.31.dist-info/RECORD
