Metadata-Version: 2.4
Name: Qubx
Version: 0.7.31
Summary: Qubx - Quantitative Trading Framework
License-File: LICENSE
Author: Dmitry Marienko
Author-email: dmitry.marienko@xlydian.com
Requires-Python: >=3.10,<4.0
Classifier: Programming Language :: Python :: 3
Classifier: Programming Language :: Python :: 3.10
Classifier: Programming Language :: Python :: 3.11
Classifier: Programming Language :: Python :: 3.12
Classifier: Programming Language :: Python :: 3.13
Classifier: Programming Language :: Python :: 3.14
Requires-Dist: aiohttp (>=3.10.11,<3.11.0)
Requires-Dist: ccxt (>=4.2.68,<5.0.0)
Requires-Dist: croniter (>=2.0.5,<3.0.0)
Requires-Dist: cython (==3.0.8)
Requires-Dist: dash (>=2.18.2,<3.0.0)
Requires-Dist: dash-bootstrap-components (>=1.6.0,<2.0.0)
Requires-Dist: gitpython (>=3.1.44,<4.0.0)
Requires-Dist: importlib-metadata
Requires-Dist: ipywidgets (>=8.1.5,<9.0.0)
Requires-Dist: jinja2 (>=3.1.0,<4.0.0)
Requires-Dist: jupyter (>=1.1.1,<2.0.0)
Requires-Dist: jupyter-console (>=6.6.3,<7.0.0)
Requires-Dist: loguru (>=0.7.2,<0.8.0)
Requires-Dist: matplotlib (>=3.8.4,<4.0.0)
Requires-Dist: msgspec (>=0.18.6,<0.19.0)
Requires-Dist: ntplib (>=0.4.0,<0.5.0)
Requires-Dist: numba (>=0.59.1,<0.60.0)
Requires-Dist: numpy (>=1.26.3,<2.0.0)
Requires-Dist: orjson (>=3.10.15,<4.0.0)
Requires-Dist: pandas (>=2.2.2,<3.0.0)
Requires-Dist: plotly (>=5.22.0,<6.0.0)
Requires-Dist: psycopg (>=3.1.18,<4.0.0)
Requires-Dist: psycopg-binary (>=3.1.19,<4.0.0)
Requires-Dist: psycopg-pool (>=3.2.2,<4.0.0)
Requires-Dist: pyarrow (>=15.0.0,<16.0.0)
Requires-Dist: pydantic (>=2.9.2,<3.0.0)
Requires-Dist: pymongo (>=4.6.1,<5.0.0)
Requires-Dist: python-binance (>=1.0.19,<2.0.0)
Requires-Dist: python-dotenv (>=1.0.0,<2.0.0)
Requires-Dist: pyyaml (>=6.0.2,<7.0.0)
Requires-Dist: qubx-bitfinex-api (>=3.0.7,<4.0.0)
Requires-Dist: qubx-lighter-api (>=0.1.5,<0.2.0)
Requires-Dist: questdb (>=2.0.3,<3.0.0)
Requires-Dist: redis (>=5.2.1,<6.0.0)
Requires-Dist: rich (>=13.9.4,<14.0.0)
Requires-Dist: scikit-learn (>=1.4.2,<2.0.0)
Requires-Dist: scipy (>=1.12.0,<2.0.0)
Requires-Dist: sortedcontainers (>=2.4.0,<3.0.0)
Requires-Dist: stackprinter (>=0.2.10,<0.3.0)
Requires-Dist: statsmodels (>=0.14.2,<0.15.0)
Requires-Dist: tabulate (>=0.9.0,<0.10.0)
Requires-Dist: textual-autocomplete (>=4.0.0,<5.0.0)
Requires-Dist: textual-serve (>=1.0.0,<2.0.0)
Requires-Dist: textual[syntax] (>=6.0.0,<7.0.0)
Requires-Dist: toml (>=0.10.2,<0.11.0)
Requires-Dist: tqdm
Requires-Dist: uvloop (>=0.22.1,<0.23.0)
Requires-Dist: websockets (==15.0.1)
Project-URL: Repository, https://github.com/xLydianSoftware/Qubx
